Metadata-Version: 1.0
Name: sobekio
Version: 0.1.0
Summary: Support reading output (.HIS) from Sobek Version 2
Home-page: http://github.com/dinhquanght/sobekio_py
Author: D. Quang Duong
Author-email: dinhquanght@gmail.com
License: GPL3
Keywords: Sobek,Sobek River,Deltares,HIS
Platform: UNKNOWN
